maleo/constants/__init__.py
maleo/constants/error.py
maleo/constants/middleware.py
maleo/constants/patterns.py
maleo/constants/status.py
maleo_constants-0.0.11.dist-info/licenses/LICENSE
maleo_constants-0.0.11.dist-info/METADATA
maleo_constants-0.0.11.dist-info/WHEEL
maleo_constants-0.0.11.dist-info/top_level.txt
maleo_constants-0.0.11.dist-info/RECORD
