Metadata-Version: 2.4
Name: maleo-constants
Version: 0.0.11
Summary: Constants package for MaleoSuite
Author-email: Agra Bima Yuda <agra@nexmedis.com>
License: Proprietary
Requires-Python: >=3.12
License-File: LICENSE
Requires-Dist: black>=25.1.0
Requires-Dist: cfgv>=3.4.0
Requires-Dist: click>=8.2.1
Requires-Dist: distlib>=0.4.0
Requires-Dist: filelock>=3.19.1
Requires-Dist: identify>=2.6.13
Requires-Dist: maleo-enums>=0.0.9
Requires-Dist: maleo-types-base>=0.0.3
Requires-Dist: maleo-types-enums>=0.0.9
Requires-Dist: mypy_extensions>=1.1.0
Requires-Dist: nodeenv>=1.9.1
Requires-Dist: packaging>=25.0
Requires-Dist: pathspec>=0.12.1
Requires-Dist: platformdirs>=4.4.0
Requires-Dist: pre_commit>=4.3.0
Requires-Dist: PyYAML>=6.0.2
Requires-Dist: virtualenv>=20.34.0
Dynamic: license-file
